pythovolve/__init__.py
pythovolve/__main__.py
pythovolve/algorithm.py
pythovolve/callbacks.py
pythovolve/crossover.py
pythovolve/individuals.py
pythovolve/mutation.py
pythovolve/plotting.py
pythovolve/problems.py
pythovolve/selection.py
pythovolve-0.1.1.dist-info/LICENSE
pythovolve-0.1.1.dist-info/METADATA
pythovolve-0.1.1.dist-info/WHEEL
pythovolve-0.1.1.dist-info/top_level.txt
pythovolve-0.1.1.dist-info/RECORD
