Metadata-Version: 2.1
Name: pythovolve
Version: 0.1.1
Summary: Object oriented framework for genetic algorithms
Home-page: https://github.com/peter-schmidbauer/pythovolve
Author: Peter Schmidbauer
Author-email: peter.schmidb@gmail.com
License: MIT
Platform: UNKNOWN
Classifier: Programming Language :: Python :: 3.6
Classifier: Programming Language :: Python :: 3.7
Classifier: License :: OSI Approved :: MIT License
Classifier: Operating System :: OS Independent
Classifier: Topic :: Scientific/Engineering :: Artificial Intelligence
Requires-Dist: matplotlib
Requires-Dist: seaborn
Requires-Dist: sympy
Requires-Dist: pandas
Requires-Dist: scipy
